objectifiedetree/__init__.py
objectifiedetree/VERSION
objectifiedetree/etree/__init__.py
objectifiedetree/etree/ElementInclude.py
objectifiedetree/etree/ElementPath.py
objectifiedetree/etree/ElementTree.py
objectifiedetree-0.0.1.dist-info/DESCRIPTION.rst
objectifiedetree-0.0.1.dist-info/METADATA
objectifiedetree-0.0.1.dist-info/metadata.json
objectifiedetree-0.0.1.dist-info/RECORD
objectifiedetree-0.0.1.dist-info/top_level.txt
objectifiedetree-0.0.1.dist-info/WHEEL
