Metadata-Version: 2.0
Name: objectifiedetree
Version: 0.0.1
Summary: Dot notation for ElementTrees
Home-page: https://github.com/arve0/objectifiedetree
Author: Arve Seljebu
Author-email: arve.seljebu@gmail.com
License: MIT
Keywords: objectifiedetree
Platform: UNKNOWN
Classifier: Development Status :: 2 - Pre-Alpha
Classifier: Intended Audience :: Developers
Classifier: License :: OSI Approved :: MIT License
Classifier: Natural Language :: English
Classifier: Programming Language :: Python :: 3
Classifier: Programming Language :: Python :: 3.4
